djangorestframework_recaptcha-0.2.0.dist-info/METADATA
djangorestframework_recaptcha-0.2.0.dist-info/RECORD
djangorestframework_recaptcha-0.2.0.dist-info/WHEEL
djangorestframework_recaptcha-0.2.0.dist-info/top_level.txt
rest_framework_recaptcha/__init__.py
rest_framework_recaptcha/compat.py
rest_framework_recaptcha/conf.py
rest_framework_recaptcha/fields.py
rest_framework_recaptcha/validators.py
rest_framework_recaptcha/locale/en/LC_MESSAGES/django.mo
rest_framework_recaptcha/locale/fr/LC_MESSAGES/django.mo
