Metadata-Version: 2.1
Name: djangorestframework-recaptcha
Version: 0.2.0
Summary: reCAPTCHA field for Django REST framework serializers.
Home-page: https://github.com/Maximilien-R/django-rest-framework-recaptcha
Author: Maximilien Raulic
Author-email: maximilien.raulic@gmail.com
License: MIT
Keywords: django rest framework recaptcha
Platform: UNKNOWN
Classifier: Development Status :: 3 - Alpha
Classifier: Framework :: Django :: 1.10
Classifier: Framework :: Django :: 1.11
Classifier: Framework :: Django :: 2.0
Classifier: Framework :: Django :: 2.1
Classifier: Intended Audience :: Developers
Classifier: License :: OSI Approved :: BSD License
Classifier: Natural Language :: English
Classifier: Programming Language :: Python :: 2
Classifier: Programming Language :: Python :: 2.7
Classifier: Programming Language :: Python :: 3
Classifier: Programming Language :: Python :: 3.4
Classifier: Programming Language :: Python :: 3.5
Classifier: Programming Language :: Python :: 3.6
Classifier: Programming Language :: Python :: 3.7
Provides-Extra: complexity
Provides-Extra: documentation
Provides-Extra: formatting
Provides-Extra: versioning
Provides-Extra: testing
Provides-Extra: style
Provides-Extra: publishing
Requires-Dist: django (>=1.10)
Requires-Dist: djangorestframework (>=3)
Requires-Dist: django-appconf
Requires-Dist: django-ipware (>=2.0.2)
Requires-Dist: pytz
Provides-Extra: complexity
Requires-Dist: xenon (==0.5.4); extra == 'complexity'
Provides-Extra: documentation
Requires-Dist: Sphinx (==1.7.5); extra == 'documentation'
Provides-Extra: formatting
Requires-Dist: black (==18.6b2); extra == 'formatting'
Provides-Extra: publishing
Requires-Dist: twine (==1.11.0); extra == 'publishing'
Provides-Extra: style
Requires-Dist: flake8 (==3.5.0); extra == 'style'
Provides-Extra: testing
Requires-Dist: pytest (==3.6.1); extra == 'testing'
Requires-Dist: pytest-cov (==2.5.1); extra == 'testing'
Requires-Dist: pytest-django (==3.3.0); extra == 'testing'
Requires-Dist: tox (==3.0.0); extra == 'testing'
Provides-Extra: versioning
Requires-Dist: bumpversion (==0.5.3); extra == 'versioning'
